gpt_utils/__init__.py
gpt_utils/case.py
gpt_utils/classify.py
gpt_utils/conversation.py
gpt_utils/core.py
gpt_utils/dechatify.py
gpt_utils/generate_stem.py
gpt_utils/leetify.py
gpt_utils/location.py
gpt_utils/number.py
gpt_utils/pluralize.py
gpt_utils/prompt.py
gpt_utils-1.4.0.dist-info/LICENSE.txt
gpt_utils-1.4.0.dist-info/METADATA
gpt_utils-1.4.0.dist-info/WHEEL
gpt_utils-1.4.0.dist-info/top_level.txt
gpt_utils-1.4.0.dist-info/RECORD
