Metadata-Version: 2.1
Name: gpt-utils
Version: 1.4.0
Summary: Collection of utilities for use with OpenAI's GPT-3 language model
Home-page: UNKNOWN
Author: Nelson Love
Author-email: nelson@nelson.love
License: MIT
Project-URL: Bug Tracker, https://github.com/nelsonlove/gpt_utils/issues
Project-URL: Changelog, https://github.com/nelsonlove/gpt_utils/blob/master/CHANGELOG.md
Platform: UNKNOWN
Classifier: Development Status :: 4 - Beta
Classifier: Intended Audience :: Developers
Classifier: License :: OSI Approved :: MIT License
Classifier: Operating System :: OS Independent
Classifier: Natural Language :: English
Classifier: Programming Language :: Python
Classifier: Programming Language :: Python :: 3.4
Classifier: Programming Language :: Python :: 3.5
Classifier: Programming Language :: Python :: 3.6
Classifier: Programming Language :: Python :: 3.7
Classifier: Programming Language :: Python :: 3.8
Classifier: Topic :: Software Development :: Libraries :: Python Modules
Classifier: Topic :: Text Editors :: Text Processing
Classifier: Topic :: Text Processing :: Linguistic
License-File: LICENSE.txt
Requires-Dist: openai
Requires-Dist: transformers
